[
    {
        "task_id": "37100001",
        "task_type": "37",
        "task_group": "0",
        "task_index": "0",
        "task_id_before": "0",
        "task_condition": "2",
        "task_value": "1",
        "reward": "5:3000211:1",
        "content": "每日登录",
        "content_param": "每日登录",
        "link": ""
    },
    {
        "task_id": "37100002",
        "task_type": "37",
        "task_group": "0",
        "task_index": "0",
        "task_id_before": "0",
        "task_condition": "37",
        "task_value": "1",
        "reward": "5:3000211:1",
        "content": "挑战公会boss1次",
        "content_param": "挑战公会boss1次",
        "link": ""
    },
    {
        "task_id": "37100003",
        "task_type": "37",
        "task_group": "0",
        "task_index": "0",
        "task_id_before": "0",
        "task_condition": "25",
        "task_value": "3",
        "reward": "5:3000211:1",
        "content": "快速挂机3次",
        "content_param": "快速挂机3次",
        "link": "4"
    },
    {
        "task_id": "37100004",
        "task_type": "37",
        "task_group": "0",
        "task_index": "0",
        "task_id_before": "0",
        "task_condition": "121",
        "task_value": "500",
        "reward": "5:3000211:1",
        "content": "累计消耗500神核",
        "content_param": "累计消耗500神核",
        "link": ""
    },
    {
        "task_id": "37100005",
        "task_type": "37",
        "task_group": "0",
        "task_index": "0",
        "task_id_before": "0",
        "task_condition": "138",
        "task_value": "500",
        "reward": "5:3000211:1",
        "content": "累计消耗500钻石",
        "content_param": "累计消耗500钻石",
        "link": ""
    }
]